linkcheckmd/__init__.py
linkcheckmd/__main__.py
linkcheckmd/base.py
linkcheckmd/coro.py
linkcheckmd/files.py
linkcheckmd/sync.py
linkcheckmd/tests/__init__.py
linkcheckmd/tests/badlink.md
linkcheckmd/tests/test_script.py
mkdocs_codecheck/__init__.py
mkdocs_codecheck/__main__.py
mkdocs_codecheck/base.py
mkdocs_codecheck/bcolors.py
mkdocs_codecheck/dotignore.py
mkdocs_codecheck/files.py
mkdocs_codecheck/handlers.py
mkdocs_codecheck/test.py
mkdocs_codecheck/tests/__init__.py
mkdocs_codecheck/tests/test_script.py
mkdocs_linkcheck/__init__.py
mkdocs_linkcheck/__main__.py
mkdocs_linkcheck/base.py
mkdocs_linkcheck/coro.py
mkdocs_linkcheck/files.py
mkdocs_linkcheck/sync.py
mkdocs_linkcheck/tests/__init__.py
mkdocs_linkcheck/tests/badlink.md
mkdocs_linkcheck/tests/test_script.py
mkdocs_codecheck-0.9.5.dist-info/LICENSE.txt
mkdocs_codecheck-0.9.5.dist-info/METADATA
mkdocs_codecheck-0.9.5.dist-info/WHEEL
mkdocs_codecheck-0.9.5.dist-info/entry_points.txt
mkdocs_codecheck-0.9.5.dist-info/top_level.txt
mkdocs_codecheck-0.9.5.dist-info/RECORD
