Metadata-Version: 2.1
Name: mkdocs-codecheck
Version: 0.9.5
Summary: Traverses a directory tree looking for code samples, then attempts to validate each code sample found.
Home-page: https://github.com/byrnereese/mkdocs-codechecker
Author: Byrne Reese
Author-email: byrne@majordojo.com
License: UNKNOWN
Keywords: code,qa,markdown,mkdocs
Platform: UNKNOWN
Classifier: Development Status :: 5 - Production/Stable
Classifier: Environment :: Console
Classifier: Framework :: AsyncIO
Classifier: Intended Audience :: Developers
Classifier: Operating System :: OS Independent
Classifier: Programming Language :: Python :: 3
Classifier: Programming Language :: Python :: Implementation :: CPython
Classifier: Topic :: Internet :: WWW/HTTP :: Site Management :: Link Checking
Requires-Python: >=3.7
Provides-Extra: lint
Requires-Dist: flake8 ; extra == 'lint'
Requires-Dist: flake8-bugbear ; extra == 'lint'
Requires-Dist: flake8-builtins ; extra == 'lint'
Requires-Dist: flake8-blind-except ; extra == 'lint'
Requires-Dist: mypy ; extra == 'lint'
Provides-Extra: requests
Requires-Dist: requests ; extra == 'requests'
Provides-Extra: tests
Requires-Dist: pytest ; extra == 'tests'
